rag_scraper/__init__.py
rag_scraper/cli.py
rag_scraper/converter.py
rag_scraper/link_extractor.py
rag_scraper/scraper.py
rag_scraper/utils.py
ragscraper-11.5.2023.dist-info/METADATA
ragscraper-11.5.2023.dist-info/WHEEL
ragscraper-11.5.2023.dist-info/RECORD
