Metadata-Version: 2.1
Name: RAGScraper
Version: 11.5.2023
Summary: RAGScraper is a Python library designed for efficient and intelligent scraping of web documentation and content. Tailored for Retrieval-Augmented Generation systems, RAGScraper extracts and preprocesses text into structured, machine-learning-ready formats. It emphasizes precision, context preservation, and ease of integration with RAG models, making it an ideal tool for developers looking to enhance AI-driven applications with rich, web-sourced knowledge.
License: MIT
Author: kdcokenny
Author-email: kenny@elapse.ai
Requires-Python: >=3.10,<4.0
Classifier: License :: OSI Approved :: MIT License
Classifier: Programming Language :: Python :: 3
Classifier: Programming Language :: Python :: 3.10
Classifier: Programming Language :: Python :: 3.11
Requires-Dist: beautifulsoup4 (>=4.12.2,<5.0.0)
Requires-Dist: html2text (>=2020.1.16,<2021.0.0)
Requires-Dist: requests (>=2.31.0,<3.0.0)
